pollencli/__init__.py
pollencli/pyline_removal/__init__.py
pollencli/pyline_removal/cli.py
pollencli_pyline_removal-0.0.5a0.dist-info/entry_points.txt
pollencli_pyline_removal-0.0.5a0.dist-info/WHEEL
pollencli_pyline_removal-0.0.5a0.dist-info/METADATA
pollencli_pyline_removal-0.0.5a0.dist-info/RECORD
