Metadata-Version: 2.1
Name: pollencli-pyline-removal
Version: 0.0.5a0
Summary: Remove lines from python file
Home-page: https://github.com/pollenjp/pollencli-pyline-removal
License: MIT
Author: pollenjp
Author-email: polleninjp@gmail.com
Requires-Python: >=3.8,<4.0
Classifier: Development Status :: 3 - Alpha
Classifier: License :: OSI Approved :: MIT License
Classifier: Programming Language :: Python :: 3
Classifier: Programming Language :: Python :: 3.10
Classifier: Programming Language :: Python :: 3.8
Classifier: Programming Language :: Python :: 3.9
Project-URL: Repository, https://github.com/pollenjp/pollencli-pyline-removal
